{
  "date": "2026-07-16",
  "time_kst": "19:30",
  "topic": "중국세관",
  "text": "중국 입국할 때 캐리어보다 위험한 게 너희 손가방 안에 있어.\n\n제일 어이없이 걸리는 게 【감기약】이야. 에페드린 들어간 한국 감기약, 중국에선 마약류 취급받을 수 있어. 약 챙길 거면 영문 처방전 같이 들고 가.\n\n먹을 것도 함정이야. 고기·계란 들어간 건 거의 다 막혀. 육포, 소시지, 고기빵, 심지어 계란 든 빵까지. 신선 과일·채소도 안 돼.\n\n현금은 위안화 2만 위안 또는 미화 5,000달러 상당 넘으면 신고 대상. 모르고 넘기면 회피로 본다.\n\n'설마 이게?' 싶은 것들이 진짜 발목 잡으니까, 짐 쌀 때 가방부터 한 번 털어봐.\n\n#중국세관",
  "sources": "📍출처·소재 (수집 2026-06-23)\nhttps://korean.shanghai.gov.cn/ko-CustomsClearance/20240319/8a4b5f67df0844a7a16bccb159ba78fe.html — 상하이시 공식 입국 통관 가이드(현금 한도·반입금지)\nhttps://kr.trip.com/guide/info/중국+반입+금지+물품.html — 2026 중국 반입금지 물품·세관 신고 가이드\nhttps://baby.tali.kr/china-customs-banned-items — 중국 입국 반입금지 품목 세관 규정 정리(약·식품)\nhttps://overseas.mofa.go.kr/cn-xian-ko/brd/m_773/view.do?seq=1240397 — 주시안 대한민국총영사관 중국 입출국 유의사항\n⚠️ 금지·제한 품목과 현금 한도는 변동 가능, 중국 해관(海关) 공식 재확인",
  "card": {
    "kicker": "중국 세관 · 반입 주의",
    "headline": "캐리어보다\n*손가방*이 위험하다",
    "body": "감기약(에페드린)→영문 처방전 필수\n고기·계란 식품, 신선 과일채소 금지\n현금 2만 위안/5천 달러 넘으면 신고\n\n짐 싸기 전 가방부터 털어봐",
    "tag": "#중국세관",
    "photoQuery": "airport luggage suitcase customs"
  }
}