{
  "date": "2026-06-29",
  "time_kst": "08:30",
  "topic": "원스톱",
  "text": "전단지 따로, 상세페이지 따로, 마케팅 또 따로 맡기다 지친 적 있지?\n⠀\n디자인이랑 마케팅이 따로 놀면 메시지가 흩어져.\n전단지 톤이랑 인스타 톤이 다르면 손님이 헷갈리거든.\n⠀\n우린 디자인부터 마케팅까지 한 손에서 간다.\n브랜드 톤 하나로 쭉 이어지게.\n⠀\n흩어진 거 모아서 정리해줄게. 대구·경북 사장님들 환영.",
  "sources": "📍출처·소재 (수집 2026-06-23)\nhttps://blog.naver.com/teamo1114/224239858533 — 채널마다 톤앤매너가 다르면 뇌가 일관성 없다고 인식한다 (끼너지 브랜딩 블로그, 2026.04)\nhttps://blog.naver.com/stars_tech_/223828727192 — 디자인·마케팅을 통합 조율하는 기획사 선택의 중요성 (붉은노을연구소 블로그, 2025.04)\nhttps://blog.naver.com/laonmarketong2022/224050141951 — 영상·포스터·온라인마케팅을 하나의 일관된 브랜드 스토리로 연결 (라온마케팅 블로그, 2025.10)\nhttps://www.threads.com/@feb.26th_/post/DIEZXNxSkuZ — 채널마다 톤·로고가 제각각이면 브랜드 파워 약해진다(일관성=신뢰) (Threads)\nhttps://www.threads.com/@biroso_happymap/post/DOi3EWCj0WC — 브랜드·브랜딩·마케팅의 연결과 차이에 대한 이야기 (Threads)\n⚠️ 통합 효과는 업종·실행력에 따라 달라짐.",
  "card": {
    "kicker": "원스톱",
    "headline": "디자인 따로 마케팅 따로?\n*메시지가 흩어진다*",
    "body": "한 손에서 톤 맞춰 쭉 이어가야\n손님 머리에 남아.",
    "tag": "원스톱 · firstdesign",
    "photoQuery": "marketing print flyer brochure design"
  }
}